langchain_gigachat/__init__.py
langchain_gigachat/chat_models/__init__.py
langchain_gigachat/chat_models/base_gigachat.py
langchain_gigachat/chat_models/gigachat.py
langchain_gigachat/embeddings/__init__.py
langchain_gigachat/embeddings/gigachat.py
langchain_gigachat/output_parsers/__init__.py
langchain_gigachat/output_parsers/gigachat_functions.py
langchain_gigachat/py.typed
langchain_gigachat/tools/__init__.py
langchain_gigachat/tools/giga_tool.py
langchain_gigachat/tools/load_prompt.py
langchain_gigachat/utils/__init__.py
langchain_gigachat/utils/function_calling.py
langchain_gigachat/utils/pydantic_generator.py
langchain_gigachat-0.3.11.dist-info/LICENSE
langchain_gigachat-0.3.11.dist-info/METADATA
langchain_gigachat-0.3.11.dist-info/WHEEL
langchain_gigachat-0.3.11.dist-info/RECORD
