Metadata-Version: 2.3
Name: langchain-gigachat
Version: 0.3.11
Summary: An integration package connecting GigaChat and LangChain
License: MIT
Requires-Python: >=3.9,<4.0
Classifier: License :: OSI Approved :: MIT License
Classifier: Programming Language :: Python :: 3
Classifier: Programming Language :: Python :: 3.9
Classifier: Programming Language :: Python :: 3.10
Classifier: Programming Language :: Python :: 3.11
Classifier: Programming Language :: Python :: 3.12
Classifier: Programming Language :: Python :: 3.13
Requires-Dist: gigachat (>=0.1.40,<0.2.0)
Requires-Dist: langchain-core (>=0.3,<0.4)
Requires-Dist: types-requests (>=2.32,<3.0)
Project-URL: Repository, https://github.com/ai-forever/langchain-gigachat
Project-URL: Source Code, https://github.com/ai-forever/langchain-gigachat/tree/master/libs/gigachat
